Encryptor/__init__.py
AES_Encryptor-2.0.dist-info/LICENSE
AES_Encryptor-2.0.dist-info/METADATA
AES_Encryptor-2.0.dist-info/WHEEL
AES_Encryptor-2.0.dist-info/top_level.txt
AES_Encryptor-2.0.dist-info/RECORD
