Metadata-Version: 2.1
Name: AES-Encryptor
Version: 2.0
Summary: Encrypt Strings And Files With AES Encryption
Home-page: https://github.com/pmk456/AES-Encryptor
Author: Patan Musthakheem
Author-email: patanmusthakheem786@gmail.com
License: UNKNOWN
Project-URL: Bug Tracker, https://github.com/pmk456/AES-Encryptor/issues
Platform: UNKNOWN
Classifier: Programming Language :: Python :: 3
Classifier: License :: OSI Approved :: Apache Software License
Classifier: Operating System :: OS Independent
Requires-Python: >=3.0
License-File: LICENSE
